glibs_jsonschema-1.0.0-py3.10-nspkg.pth
glibs/jsonschema.py
glibs_jsonschema-1.0.0.dist-info/METADATA
glibs_jsonschema-1.0.0.dist-info/WHEEL
glibs_jsonschema-1.0.0.dist-info/namespace_packages.txt
glibs_jsonschema-1.0.0.dist-info/top_level.txt
glibs_jsonschema-1.0.0.dist-info/RECORD
